.editorconfig
.gitignore
.travis.yml
LICENSE
Makefile
Pipfile
Pipfile.lock
README.rst
setup.py
start.sh
.vscode/settings.json
test/__init__.py
test/test_client.py
test/test_header.py
test/udp_echo_server.py
udprelay/__init__.py
udprelay/client.py
udprelay/header.py
udprelay/logger.py
udprelay/server.py
udprelay.egg-info/PKG-INFO
udprelay.egg-info/SOURCES.txt
udprelay.egg-info/dependency_links.txt
udprelay.egg-info/requires.txt
udprelay.egg-info/top_level.txt