Metadata-Version: 1.0
Name: udprelay
Version: 0.2.1
Summary: another simple udp realy server and client
Home-page: https://github.com/whatArePeopleDownloading/udpRelay
Author: meta Z
Author-email: zycode277@gmail.com
License: MIT
Platform: UNKNOWN
